jinja2_slug/__init__.py
jinja2_slug/core.py
jinja2_slug-0.2.0.dist-info/LICENSE
jinja2_slug-0.2.0.dist-info/WHEEL
jinja2_slug-0.2.0.dist-info/METADATA
jinja2_slug-0.2.0.dist-info/RECORD
