Metadata-Version: 2.1
Name: jinja2-slug
Version: 0.2.0
Summary: Jinja2 Extension for creating slugs
License: MIT
Author: Marvin Steadfast
Author-email: marvin@xsteadfastx.org
Requires-Python: >=3.5,<4.0
Classifier: License :: OSI Approved :: MIT License
Classifier: Programming Language :: Python :: 3
Classifier: Programming Language :: Python :: 3.5
Classifier: Programming Language :: Python :: 3.6
Classifier: Programming Language :: Python :: 3.7
Requires-Dist: jinja2 (>=2.10,<3.0)
Requires-Dist: unicode-slugify (>=0.1.3,<0.2.0)
